<Sql TableName="AFSetup" TableSchemaXml="#CDATA">
    <CDATA name="TableSchemaXml"><![CDATA[<table name="AFSetUp">
  <col name="AFAccessKey" type="VarChar(100)" nullable="true" />
  <col name="AFSecretKey" type="VarChar(100)" nullable="true" />
  <col name="AFBucketName" type="VarChar(100)" nullable="true" />
  <col name="AFDirectoryName" type="VarChar(100)" nullable="true" />
  <col name="AFOutDirectoryName" type="VarChar(100)" nullable="true" />
  <col name="CompanyID" type="Int" default="Zero" />
  <col name="CreatedByID" type="UniqueIdentifier" />
  <col name="CreatedByScreenID" type="Char(8)" />
  <col name="CreatedDateTime" type="DateTime" />
  <col name="LastModifiedByID" type="UniqueIdentifier" />
  <col name="LastModifiedByScreenID" type="Char(8)" />
  <col name="LastModifiedDateTime" type="DateTime" />
  <col name="tstamp" type="Timestamp" />
  <index name="PK__tmp_ms_x__2D971C4CFBF97229" clustered="true" primary="true" unique="true">
    <col name="CompanyID" />
  </index>
</table>]]></CDATA>
</Sql>